jackofalltrades/__init__.py
jackofalltrades/Errors/__init__.py
jackofalltrades/Errors/error.py
jackofalltrades/Models/Regression.py
jackofalltrades/Models/__init__.py
jackofalltrades/datasets/BTC-USD.csv
jackofalltrades/datasets/Real estate.csv
jackofalltrades/datasets/__init__.py
jackofalltrades/datasets/all_fuels_data.csv
jackofalltrades/datasets/dataset.py
jackofalltrades/datasets/london_house_prices.csv
jackofalltrades/test/__init__.py
jackofalltrades/test/tests.py
jackofalltrades-0.0.1.dist-info/LICENSE.txt
jackofalltrades-0.0.1.dist-info/METADATA
jackofalltrades-0.0.1.dist-info/WHEEL
jackofalltrades-0.0.1.dist-info/top_level.txt
jackofalltrades-0.0.1.dist-info/RECORD
