Metadata-Version: 2.1
Name: jackofalltrades
Version: 0.0.1
Summary: Tired of complex machine learning libraries? Introducing jackofalltrades, a streamlined Python package designed to make machine learning accessible for everyone.
Home-page: https://github.com/lazy-punk/jackofalltrades
Author: Sane Punk
Author-email: Sane Punk <punk00pp@gmail.com>
License: MIT
Project-URL: homepage, https://github.com/lazy-punk/jackofalltrades
Project-URL: Documentation, https://github.com/lazy-punk/jackofalltrades
Classifier: Development Status :: 3 - Alpha
Classifier: Intended Audience :: Developers
Classifier: Intended Audience :: Education
Classifier: Intended Audience :: Science/Research
Classifier: License :: OSI Approved :: MIT License
Classifier: Programming Language :: Python :: 3
Classifier: Topic :: Scientific/Engineering :: Artificial Intelligence
License-File: LICENSE.txt
Requires-Dist: pandas >=2.2.2
Requires-Dist: numpy >=1.26.4
Requires-Dist: scikit-learn >=1.5.0
Requires-Dist: matplotlib >=3.9.0
Requires-Dist: jax[cpu] >=0.4.28
Requires-Dist: tqdm >=4.66.4
